./PKG-INFO
./README.md
./__init__.py
./pyproject.toml
./server.py
./setup.py
./.github/workflows/pypi-publish.yml
bach_jsearch-1.0.3.dist-info/METADATA
bach_jsearch-1.0.3.dist-info/WHEEL
bach_jsearch-1.0.3.dist-info/entry_points.txt
bach_jsearch-1.0.3.dist-info/RECORD
