Metadata-Version: 2.4
Name: bach-jsearch
Version: 1.0.3
Summary: RapidAPI: letscrape-6bRBa3QguO5/jsearch
Project-URL: Homepage, https://github.com/bachstudio/bach-jsearch
Project-URL: Repository, https://github.com/bachstudio/bach-jsearch
Project-URL: Documentation, https://github.com/bachstudio/bach-jsearch#readme
Requires-Python: >=3.10
Requires-Dist: fastmcp>=2.0.0
Requires-Dist: httpx>=0.25.0
Provides-Extra: dev
Requires-Dist: black>=23.0.0; extra == 'dev'
Requires-Dist: pytest>=7.0.0; extra == 'dev'
